{
	"mestemplates": [
		{
			"category": "pricing",
			"code": "bc11e5d490ff74357c512ab6a4828d5d",
			"url": "/tplsnew/OKhero.html",
			"visibility": true,
			"type": "rj_section_container"
		},
		{
			"category": "team",
			"code": "bc28e5d490ff74357c512ab6a4828d5d",
			"url": "/tplsnew/OKhero2.html",
			"visibility": true,
			"type": "rj_section_container"
		},
		{
			"category": "pricing",
			"code": "fac4b42872f9bdfd7653763740a62a19",
			"url": "/tplsnew/OKhero2.html",
			"visibility": true,
			"type": "rj_section_container"
		},
		{
			"category": "team",
			"code": "3456789",
			"url": "/tplsnew/OKhero.html",
			"visibility": true,
			"type": "rj_section_container"
		},
		{
			"category": "team",
			"code": "e93d4e11c96f21abca4e593dcc1117e2",
			"url": "https://vakcin.com/assets/images/KvasBaginnature_1024x1024@2x.jpg",
			"visibility": true,
			"type": "rj_section_container"
		},
		{
			"visibility": true,
			"category": "hero",
			"type": "rj_hero",
			"code": "1",
			"url": "/tplsnew/main_title.html"
		},
		{
			"category": "pricing",
			"code": "fac4b42872f9bdfd7653763740a62a12",
			"url": "https://vakcin.com/assets/images/KvasBaginnature_1024x1024@2x.jpg",
			"visibility": true,
			"type": "rj_section_container"
		},
		{
			"category": "invisible",
			"code": "345678",
			"url": "url none",
			"visibility": false,
			"type": "rj_section_container"
		},
		{
			"visibility": true,
			"category": "Presentation équipe",
			"type": "rj_main_title",
			"code": "hero2",
			"url": "/tplsnew/main_title_2.html"
		},
		{
			"visibility": true,
			"category": "Attract",
			"type": "rj_hero",
			"url": "/tplsnew/main_title_divs.html"
		},
		{
			"visibility": true,
			"category": "Attract",
			"type": "rj_main_title",
			"url": "/tplsnew/main_title_is-classic_small.html"
		},
		{
			"visibility": true,
			"category": "Title",
			"type": "rj_main_title",
			"code": "45678",
			"url": "/tplsnew/main_title_btn.html"
		},
		{
			"visibility": true,
			"category": "Title",
			"type": "rj_main_title",
			"code": "AAA",
			"url": "/tplsnew/boot1-mavo.html"
		},
		{
			"visibility": true,
			"category": "nav",
			"type": "rj_nav",
			"url": "/tplsnew/hero_nav1.html",
			"page": "Principale"
		},
		{
			"visibility": true,
			"category": "nav",
			"type": "rj_nav",
			"url": "/tplsnew/hero_nav2.html",
			"page": "Principale"
		}
	]
}